sensitive_data_logging/__init__.py
sensitive_data_logging/__version__.py
sensitive_data_logging/configurators.py
sensitive_data_logging/formatters.py
sensitive_data_logging/loggers.py
sensitive_data_logging-1.0.0.dist-info/LICENSE
sensitive_data_logging-1.0.0.dist-info/METADATA
sensitive_data_logging-1.0.0.dist-info/WHEEL
sensitive_data_logging-1.0.0.dist-info/top_level.txt
sensitive_data_logging-1.0.0.dist-info/RECORD
