Metadata-Version: 2.1
Name: sensitive-data-logging
Version: 1.0.0
Summary: Utils for logging sensitive data.
Author: IIIT
Author-email: github@iiit.pl
License: UNKNOWN
Keywords: sensitive data logging
Platform: UNKNOWN
Classifier: Intended Audience :: Developers
Classifier: Programming Language :: Python :: 3.6
Classifier: Programming Language :: Python :: 3.7
Classifier: Programming Language :: Python :: 3.8
Classifier: Programming Language :: Python :: 3.9
Requires-Python: >=3.6.*
License-File: LICENSE
